pygeofilter/__init__.py
pygeofilter/ast.py
pygeofilter/cli.py
pygeofilter/cql2.py
pygeofilter/util.py
pygeofilter/values.py
pygeofilter/version.py
pygeofilter/backends/__init__.py
pygeofilter/backends/evaluator.py
pygeofilter/backends/optimize.py
pygeofilter/backends/cql2_json/__init__.py
pygeofilter/backends/cql2_json/evaluate.py
pygeofilter/backends/django/__init__.py
pygeofilter/backends/django/evaluate.py
pygeofilter/backends/django/filters.py
pygeofilter/backends/elasticsearch/__init__.py
pygeofilter/backends/elasticsearch/evaluate.py
pygeofilter/backends/elasticsearch/util.py
pygeofilter/backends/geopandas/__init__.py
pygeofilter/backends/geopandas/evaluate.py
pygeofilter/backends/geopandas/filters.py
pygeofilter/backends/native/__init__.py
pygeofilter/backends/native/evaluate.py
pygeofilter/backends/opensearch/__init__.py
pygeofilter/backends/opensearch/evaluate.py
pygeofilter/backends/opensearch/util.py
pygeofilter/backends/oraclesql/__init__.py
pygeofilter/backends/oraclesql/evaluate.py
pygeofilter/backends/solr/__init__.py
pygeofilter/backends/solr/evaluate.py
pygeofilter/backends/solr/util.py
pygeofilter/backends/sql/__init__.py
pygeofilter/backends/sql/evaluate.py
pygeofilter/backends/sqlalchemy/__init__.py
pygeofilter/backends/sqlalchemy/evaluate.py
pygeofilter/backends/sqlalchemy/filters.py
pygeofilter/parsers/__init__.py
pygeofilter/parsers/iso8601.lark
pygeofilter/parsers/iso8601.py
pygeofilter/parsers/wkt.lark
pygeofilter/parsers/wkt.py
pygeofilter/parsers/cql2_json/__init__.py
pygeofilter/parsers/cql2_json/parser.py
pygeofilter/parsers/cql2_text/__init__.py
pygeofilter/parsers/cql2_text/grammar.lark
pygeofilter/parsers/cql2_text/parser.py
pygeofilter/parsers/cql_json/__init__.py
pygeofilter/parsers/cql_json/parser.py
pygeofilter/parsers/ecql/__init__.py
pygeofilter/parsers/ecql/grammar.lark
pygeofilter/parsers/ecql/parser.py
pygeofilter/parsers/fes/__init__.py
pygeofilter/parsers/fes/base.py
pygeofilter/parsers/fes/gml.py
pygeofilter-0.3.3.dist-info/licenses/LICENSE
pygeofilter-0.3.3.dist-info/METADATA
pygeofilter-0.3.3.dist-info/WHEEL
pygeofilter-0.3.3.dist-info/entry_points.txt
pygeofilter-0.3.3.dist-info/top_level.txt
pygeofilter-0.3.3.dist-info/RECORD
