Metadata-Version: 2.4
Name: pygeofilter
Version: 0.3.3
Summary: pygeofilter is a pure Python parser implementation of OGC filtering standards
Home-page: https://github.com/geopython/pygeofilter
Author: Fabian Schindler
Author-email: fabian.schindler@eox.at
License: MIT
Classifier: Development Status :: 3 - Alpha
Classifier: Intended Audience :: Developers
Classifier: Topic :: Scientific/Engineering :: GIS
Classifier: License :: OSI Approved :: MIT License
Classifier: Programming Language :: Python :: 3.8
Classifier: Programming Language :: Python :: 3.9
Classifier: Programming Language :: Python :: 3.10
Classifier: Programming Language :: Python :: 3.11
Classifier: Programming Language :: Python :: 3.12
Classifier: Programming Language :: Python :: 3.13
License-File: LICENSE
Requires-Dist: click
Requires-Dist: dateparser
Requires-Dist: lark
Requires-Dist: pygeoif>=1.0.0
Provides-Extra: backend-django
Requires-Dist: django; extra == "backend-django"
Provides-Extra: backend-sqlalchemy
Requires-Dist: geoalchemy2; extra == "backend-sqlalchemy"
Requires-Dist: sqlalchemy; extra == "backend-sqlalchemy"
Provides-Extra: backend-native
Requires-Dist: shapely; extra == "backend-native"
Provides-Extra: backend-elasticsearch
Requires-Dist: elasticsearch; extra == "backend-elasticsearch"
Requires-Dist: elasticsearch-dsl; extra == "backend-elasticsearch"
Provides-Extra: backend-opensearch
Requires-Dist: opensearch-py; extra == "backend-opensearch"
Requires-Dist: opensearch-dsl; extra == "backend-opensearch"
Provides-Extra: fes
Requires-Dist: pygml>=0.2; extra == "fes"
Dynamic: author
Dynamic: author-email
Dynamic: classifier
Dynamic: description
Dynamic: description-content-type
Dynamic: home-page
Dynamic: license
Dynamic: license-file
Dynamic: provides-extra
Dynamic: requires-dist
Dynamic: summary
